howlongtobeatpy/HTMLRequests.py
howlongtobeatpy/HowLongToBeat.py
howlongtobeatpy/HowLongToBeatEntry.py
howlongtobeatpy/JSONResultParser.py
howlongtobeatpy/__init__.py
howlongtobeatpy-1.0.17.dist-info/LICENSE.md
howlongtobeatpy-1.0.17.dist-info/METADATA
howlongtobeatpy-1.0.17.dist-info/WHEEL
howlongtobeatpy-1.0.17.dist-info/top_level.txt
howlongtobeatpy-1.0.17.dist-info/RECORD
