Metadata-Version: 2.2
Name: howlongtobeatpy
Version: 1.0.17
Summary: A Python API for How Long to Beat
Home-page: https://github.com/ScrappyCocco/HowLongToBeat-PythonAPI
Author: ScrappyCocco
License: MIT
Keywords: howlongtobeat gaming steam uplay origin time length how long to beat
License-File: LICENSE.md
Requires-Dist: aiohttp>=3.11.10
Requires-Dist: requests>=2.32.3
Requires-Dist: aiounittest>=1.4.2
Requires-Dist: fake_useragent>=2.0.3
Requires-Dist: beautifulsoup4>=4.12.3
Dynamic: author
Dynamic: description
Dynamic: description-content-type
Dynamic: home-page
Dynamic: keywords
Dynamic: license
Dynamic: requires-dist
Dynamic: summary
